Devil/DevilTop.py
Devil/__init__.py
Devil/arDev.py
NASRHACKER-20.dist-info/METADATA
NASRHACKER-20.dist-info/WHEEL
NASRHACKER-20.dist-info/top_level.txt
NASRHACKER-20.dist-info/RECORD
