Metadata-Version: 2.1
Name: NASRHACKER
Version: 20
Summary: libDevil python bindings
Download-URL: http://llvm.org/releases/download.html
Author: Nasr
License: Apache-2.0 with LLVM exception
Keywords: llvm,Nasr,libDevil
Classifier: Intended Audience :: Developers
Classifier: License :: OSI Approved :: Apache Software License
Classifier: Development Status :: 5 - Production/Stable
Classifier: Topic :: Software Development :: Compilers
Classifier: Programming Language :: Python :: 3
